ft_yde_goes_package/__init__.py
ft_yde_goes_package/count_in_list.py
ft_yde_goes_package-0.0.2.dist-info/LICENSE
ft_yde_goes_package-0.0.2.dist-info/METADATA
ft_yde_goes_package-0.0.2.dist-info/WHEEL
ft_yde_goes_package-0.0.2.dist-info/top_level.txt
ft_yde_goes_package-0.0.2.dist-info/RECORD
