Metadata-Version: 2.1
Name: ft-yde-goes-package
Version: 0.0.2
Summary: A sample test package
Author-email: Ygor de Goes Sena <yde-goes@student.42sp.org.br>
Maintainer-email: Ygor de Goes Sena <yde-goes@student.42sp.org.br>
License: MIT License
Project-URL: Homepage, https://github.com/ygor-sena/42cursus-python-for-data-science
Project-URL: Documentation, https://github.com/ygor-sena/42cursus-python-for-data-science/tree/main/D00/ex09
Keywords: 42school,ft_package
Classifier: Development Status :: 4 - Beta
Classifier: Topic :: Software Development :: Build Tools
Classifier: License :: OSI Approved :: MIT License
Classifier: Programming Language :: Python :: 3
Classifier: Programming Language :: Python :: 3.8
Classifier: Programming Language :: Python :: 3.9
Classifier: Programming Language :: Python :: 3.10
Requires-Python: >=3.8
License-File: LICENSE
